deltacalc/Main.py
deltacalc/Trainer.py
deltacalc/__init__.py
deltacalc-1.1.2.dist-info/METADATA
deltacalc-1.1.2.dist-info/WHEEL
deltacalc-1.1.2.dist-info/top_level.txt
deltacalc-1.1.2.dist-info/RECORD
